[{
        "code": "A1",
        "alternatif": "Sepatu 1",
        "criteria": "4",
        "value": [
            3,
            5,
            3,
            1
        ]
    },
    {
        "code": "A2",
        "alternatif": "Sepatu 2",
        "criteria": "4",
        "value": [
            4,
            3,
            2,
            3
        ]
    },
    {
        "code": "A3",
        "alternatif": "Sepatu 3",
        "criteria": "4",
        "value": [
            5,
            4,
            5,
            1
        ]
    }
]